pygeobase/__init__.py
pygeobase/io_base.py
pygeobase/object_base.py
pygeobase/utils.py
pygeobase-0.6.3.dist-info/LICENSE.txt
pygeobase-0.6.3.dist-info/METADATA
pygeobase-0.6.3.dist-info/WHEEL
pygeobase-0.6.3.dist-info/top_level.txt
pygeobase-0.6.3.dist-info/RECORD
