Metadata-Version: 2.1
Name: pygeobase
Version: 0.6.3
Summary: Base class definition
Home-page: https://tuwien.at/mg/geo/
Author: TU Wien
Author-email: remote.sensing@geo.tuwien.ac.at
License: MIT
Project-URL: Documentation, https://pygeobase.readthedocs.org/
Platform: any
Classifier: Development Status :: 4 - Beta
Classifier: Programming Language :: Python
Requires-Python: >=3.6
License-File: LICENSE.txt
Requires-Dist: numpy
Requires-Dist: pygeogrids >=0.5.1
Requires-Dist: importlib-metadata ; python_version < "3.8"
Provides-Extra: testing
Requires-Dist: pytest ; extra == 'testing'
Requires-Dist: pytest-cov ; extra == 'testing'
